CHANGES.txt
LICENSE.txt
MANIFEST.in
README.txt
setup.py
js/__init__.py
js.i18n.egg-info/PKG-INFO
js.i18n.egg-info/SOURCES.txt
js.i18n.egg-info/dependency_links.txt
js.i18n.egg-info/entry_points.txt
js.i18n.egg-info/namespace_packages.txt
js.i18n.egg-info/not-zip-safe
js.i18n.egg-info/requires.txt
js.i18n.egg-info/top_level.txt
js/i18n/__init__.py
js/i18n/test_i18n.txt
js/i18n/resources/i18n.js
js/i18n/resources/i18n.min.js