Metadata-Version: 1.0
Name: js.i18n
Version: 0.0.0
Summary: fanstatic i18n-js bundle
Home-page: UNKNOWN
Author: Moriyoshi Koizumi
Author-email: mozo@mozo.jp
License: MIT
Platform: UNKNOWN
